[{"TeamID":1610612758,"SEASON":"2000","LeagueID":"00","PLAYER":"Chris Webber","NICKNAME":"Chris","PLAYER_SLUG":"chris-webber","NUM":"4","POSITION":"F","HEIGHT":"6-10","WEIGHT":"245","BIRTH_DATE":"MAR 01, 1973","AGE":28.0,"EXP":"7","SCHOOL":"Michigan","PLAYER_ID":185,"HOW_ACQUIRED":null},{"TeamID":1610612758,"SEASON":"2000","LeagueID":"00","PLAYER":"Hedo Turkoglu","NICKNAME":"Hedo","PLAYER_SLUG":"hedo-turkoglu","NUM":"5","POSITION":"F","HEIGHT":"6-8","WEIGHT":"220","BIRTH_DATE":"MAR 19, 1979","AGE":22.0,"EXP":"R","SCHOOL":"Efes Pilsen","PLAYER_ID":2045,"HOW_ACQUIRED":null},{"TeamID":1610612758,"SEASON":"2000","LeagueID":"00","PLAYER":"Doug Christie","NICKNAME":"Doug","PLAYER_SLUG":"doug-christie","NUM":"13","POSITION":"G-F","HEIGHT":"6-6","WEIGHT":"205","BIRTH_DATE":"MAY 09, 1970","AGE":31.0,"EXP":"8","SCHOOL":"Pepperdine","PLAYER_ID":57,"HOW_ACQUIRED":null},{"TeamID":1610612758,"SEASON":"2000","LeagueID":"00","PLAYER":"Darrick Martin","NICKNAME":"Darrick","PLAYER_SLUG":"darrick-martin","NUM":"15","POSITION":"G","HEIGHT":"5-11","WEIGHT":"170","BIRTH_DATE":"MAR 06, 1971","AGE":30.0,"EXP":"6","SCHOOL":"UCLA","PLAYER_ID":239,"HOW_ACQUIRED":null},{"TeamID":1610612758,"SEASON":"2000","LeagueID":"00","PLAYER":"Peja Stojakovic","NICKNAME":"Peja","PLAYER_SLUG":"peja-stojakovic","NUM":"16","POSITION":"F","HEIGHT":"6-9","WEIGHT":"229","BIRTH_DATE":"JUN 09, 1977","AGE":24.0,"EXP":"2","SCHOOL":"PAOK","PLAYER_ID":978,"HOW_ACQUIRED":null},{"TeamID":1610612758,"SEASON":"2000","LeagueID":"00","PLAYER":"Jon Barry","NICKNAME":"Jon","PLAYER_SLUG":"jon-barry","NUM":"20","POSITION":"G","HEIGHT":"6-5","WEIGHT":"210","BIRTH_DATE":"JUL 25, 1969","AGE":31.0,"EXP":"8","SCHOOL":"Georgia Tech","PLAYER_ID":468,"HOW_ACQUIRED":null},{"TeamID":1610612758,"SEASON":"2000","LeagueID":"00","PLAYER":"Vlade Divac","NICKNAME":"Vlade","PLAYER_SLUG":"vlade-divac","NUM":"21","POSITION":"C","HEIGHT":"7-1","WEIGHT":"260","BIRTH_DATE":"FEB 03, 1968","AGE":33.0,"EXP":"11","SCHOOL":"Partizan","PLAYER_ID":124,"HOW_ACQUIRED":null},{"TeamID":1610612758,"SEASON":"2000","LeagueID":"00","PLAYER":"Bobby Jackson","NICKNAME":"Bobby","PLAYER_SLUG":"bobby-jackson","NUM":"24","POSITION":"G","HEIGHT":"6-1","WEIGHT":"185","BIRTH_DATE":"MAR 13, 1973","AGE":28.0,"EXP":"3","SCHOOL":"Minnesota","PLAYER_ID":1517,"HOW_ACQUIRED":null},{"TeamID":1610612758,"SEASON":"2000","LeagueID":"00","PLAYER":"Nick Anderson","NICKNAME":"Nick","PLAYER_SLUG":"nick-anderson","NUM":"25","POSITION":"F-G","HEIGHT":"6-6","WEIGHT":"228","BIRTH_DATE":"JAN 20, 1968","AGE":33.0,"EXP":"11","SCHOOL":"Illinois","PLAYER_ID":98,"HOW_ACQUIRED":null},{"TeamID":1610612758,"SEASON":"2000","LeagueID":"00","PLAYER":"Scot Pollard","NICKNAME":"Scot","PLAYER_SLUG":"scot-pollard","NUM":"31","POSITION":"F-C","HEIGHT":"6-11","WEIGHT":"265","BIRTH_DATE":"FEB 12, 1975","AGE":26.0,"EXP":"3","SCHOOL":"Kansas","PLAYER_ID":1513,"HOW_ACQUIRED":null},{"TeamID":1610612758,"SEASON":"2000","LeagueID":"00","PLAYER":"Lawrence Funderburke","NICKNAME":"Lawrence","PLAYER_SLUG":"lawrence-funderburke","NUM":"51","POSITION":"F","HEIGHT":"6-9","WEIGHT":"230","BIRTH_DATE":"DEC 15, 1970","AGE":30.0,"EXP":"3","SCHOOL":"Ohio State","PLAYER_ID":1444,"HOW_ACQUIRED":null},{"TeamID":1610612758,"SEASON":"2000","LeagueID":"00","PLAYER":"Jason Williams","NICKNAME":"Jason","PLAYER_SLUG":"jason-williams","NUM":"55","POSITION":"G","HEIGHT":"6-1","WEIGHT":"190","BIRTH_DATE":"NOV 18, 1975","AGE":25.0,"EXP":"2","SCHOOL":"Florida","PLAYER_ID":1715,"HOW_ACQUIRED":null}]