[{"TeamID":1610612759,"SEASON":"2012","LeagueID":"00","PLAYER":"Tracy McGrady","NICKNAME":"Tracy","PLAYER_SLUG":"tracy-mcgrady","NUM":"1","POSITION":"G-F","HEIGHT":"6-8","WEIGHT":"225","BIRTH_DATE":"MAY 24, 1979","AGE":34.0,"EXP":"15","SCHOOL":"Mount Zion Christian Academy (NC)","PLAYER_ID":1503,"HOW_ACQUIRED":null},{"TeamID":1610612759,"SEASON":"2012","LeagueID":"00","PLAYER":"Kawhi Leonard","NICKNAME":"Kawhi","PLAYER_SLUG":"kawhi-leonard","NUM":"2","POSITION":"F-G","HEIGHT":"6-7","WEIGHT":"225","BIRTH_DATE":"JUN 29, 1991","AGE":22.0,"EXP":"1","SCHOOL":"San Diego State","PLAYER_ID":202695,"HOW_ACQUIRED":null},{"TeamID":1610612759,"SEASON":"2012","LeagueID":"00","PLAYER":"Danny Green","NICKNAME":"Danny","PLAYER_SLUG":"danny-green","NUM":"4","POSITION":"G-F","HEIGHT":"6-6","WEIGHT":"210","BIRTH_DATE":"JUN 22, 1987","AGE":26.0,"EXP":"3","SCHOOL":"North Carolina","PLAYER_ID":201980,"HOW_ACQUIRED":null},{"TeamID":1610612759,"SEASON":"2012","LeagueID":"00","PLAYER":"Cory Joseph","NICKNAME":"Cory","PLAYER_SLUG":"cory-joseph","NUM":"5","POSITION":"G","HEIGHT":"6-3","WEIGHT":"185","BIRTH_DATE":"AUG 20, 1991","AGE":21.0,"EXP":"1","SCHOOL":"Texas","PLAYER_ID":202709,"HOW_ACQUIRED":null},{"TeamID":1610612759,"SEASON":"2012","LeagueID":"00","PLAYER":"Patty Mills","NICKNAME":"Patty","PLAYER_SLUG":"patty-mills","NUM":"8","POSITION":"G","HEIGHT":"6-0","WEIGHT":"185","BIRTH_DATE":"AUG 11, 1988","AGE":24.0,"EXP":"3","SCHOOL":"St. Mary's","PLAYER_ID":201988,"HOW_ACQUIRED":null},{"TeamID":1610612759,"SEASON":"2012","LeagueID":"00","PLAYER":"Tony Parker","NICKNAME":"Tony","PLAYER_SLUG":"tony-parker","NUM":"9","POSITION":"G","HEIGHT":"6-2","WEIGHT":"185","BIRTH_DATE":"MAY 17, 1982","AGE":31.0,"EXP":"11","SCHOOL":"Paris Basket Racing","PLAYER_ID":2225,"HOW_ACQUIRED":null},{"TeamID":1610612759,"SEASON":"2012","LeagueID":"00","PLAYER":"Gary Neal","NICKNAME":"Gary","PLAYER_SLUG":"gary-neal","NUM":"14","POSITION":"G","HEIGHT":"6-4","WEIGHT":"210","BIRTH_DATE":"OCT 03, 1984","AGE":28.0,"EXP":"2","SCHOOL":"Towson","PLAYER_ID":202390,"HOW_ACQUIRED":null},{"TeamID":1610612759,"SEASON":"2012","LeagueID":"00","PLAYER":"Matt Bonner","NICKNAME":"Matt","PLAYER_SLUG":"matt-bonner","NUM":"15","POSITION":"F-C","HEIGHT":"6-10","WEIGHT":"235","BIRTH_DATE":"APR 05, 1980","AGE":33.0,"EXP":"8","SCHOOL":"Florida","PLAYER_ID":2588,"HOW_ACQUIRED":null},{"TeamID":1610612759,"SEASON":"2012","LeagueID":"00","PLAYER":"Aron Baynes","NICKNAME":"Aron","PLAYER_SLUG":"aron-baynes","NUM":"16","POSITION":"F-C","HEIGHT":"6-10","WEIGHT":"260","BIRTH_DATE":"DEC 09, 1986","AGE":26.0,"EXP":"R","SCHOOL":"Washington State","PLAYER_ID":203382,"HOW_ACQUIRED":null},{"TeamID":1610612759,"SEASON":"2012","LeagueID":"00","PLAYER":"Manu Ginobili","NICKNAME":"Manu","PLAYER_SLUG":"manu-ginobili","NUM":"20","POSITION":"G","HEIGHT":"6-6","WEIGHT":"205","BIRTH_DATE":"JUL 28, 1977","AGE":35.0,"EXP":"10","SCHOOL":"Virtus Bologna","PLAYER_ID":1938,"HOW_ACQUIRED":null},{"TeamID":1610612759,"SEASON":"2012","LeagueID":"00","PLAYER":"Tim Duncan","NICKNAME":"Tim","PLAYER_SLUG":"tim-duncan","NUM":"21","POSITION":"F","HEIGHT":"6-11","WEIGHT":"255","BIRTH_DATE":"APR 25, 1976","AGE":37.0,"EXP":"15","SCHOOL":"Wake Forest","PLAYER_ID":1495,"HOW_ACQUIRED":null},{"TeamID":1610612759,"SEASON":"2012","LeagueID":"00","PLAYER":"Tiago Splitter","NICKNAME":"Tiago","PLAYER_SLUG":"tiago-splitter","NUM":"22","POSITION":"C","HEIGHT":"6-11","WEIGHT":"240","BIRTH_DATE":"JAN 01, 1985","AGE":28.0,"EXP":"2","SCHOOL":"Bilbao","PLAYER_ID":201168,"HOW_ACQUIRED":null},{"TeamID":1610612759,"SEASON":"2012","LeagueID":"00","PLAYER":"Nando De Colo","NICKNAME":"Nando","PLAYER_SLUG":"nando-de-colo","NUM":"25","POSITION":"G","HEIGHT":"6-5","WEIGHT":"200","BIRTH_DATE":"JUN 23, 1987","AGE":26.0,"EXP":"R","SCHOOL":"Valencia","PLAYER_ID":201986,"HOW_ACQUIRED":null},{"TeamID":1610612759,"SEASON":"2012","LeagueID":"00","PLAYER":"Boris Diaw","NICKNAME":"Boris","PLAYER_SLUG":"boris-diaw","NUM":"33","POSITION":"C-F","HEIGHT":"6-8","WEIGHT":"235","BIRTH_DATE":"APR 16, 1982","AGE":31.0,"EXP":"9","SCHOOL":"Pau Orthez","PLAYER_ID":2564,"HOW_ACQUIRED":null},{"TeamID":1610612759,"SEASON":"2012","LeagueID":"00","PLAYER":"DeJuan Blair","NICKNAME":"DeJuan","PLAYER_SLUG":"dejuan-blair","NUM":"45","POSITION":"C","HEIGHT":"6-7","WEIGHT":"270","BIRTH_DATE":"APR 22, 1989","AGE":24.0,"EXP":"3","SCHOOL":"Pittsburgh","PLAYER_ID":201971,"HOW_ACQUIRED":null}]